{
  "_format": "hh-sol-cache-2",
  "files": {
    "/Users/Sebas/hh-fcc/hardhat-defi-fcc/contracts/interfaces/IWeth.sol": {
      "lastModificationDate": 1719286636611,
      "contentHash": "e75c566c95d31a2f9e90b83ed0b04c14",
      "sourceName": "contracts/interfaces/IWeth.sol",
      "solcConfig": {
        "version": "0.4.19",
        "settings": {
          "optimizer": {
            "enabled": true,
            "runs": 1000000
          },
          "metadata": {
            "bytecodeHash": "none"
          },
          "outputSelection": {
            "*": {
              "*": [
                "abi",
                "evm.bytecode",
                "evm.deployedBytecode",
                "evm.methodIdentifiers",
                "metadata"
              ],
              "": [
                "ast"
              ]
            }
          }
        }
      },
      "imports": [],
      "versionPragmas": [
        "^0.4.19"
      ],
      "artifacts": [
        "IWeth"
      ]
    }
  }
}
